{
  "ComponentIndexes": {
    "Bottom Navigation": 29,
    "Bottom Navigation_1": 23,
    "Bottom Navigation_10": 9,
    "Bottom Navigation_11": 4,
    "Bottom Navigation_12": 23,
    "Bottom Navigation_13": 21,
    "Bottom Navigation_14": 22,
    "Bottom Navigation_15": 21,
    "Bottom Navigation_16": 21,
    "Bottom Navigation_17": 21,
    "Bottom Navigation_18": 21,
    "Bottom Navigation_19": 21,
    "Bottom Navigation_2": 4,
    "Bottom Navigation_20": 21,
    "Bottom Navigation_21": 4,
    "Bottom Navigation_22": 4,
    "Bottom Navigation_23": 4,
    "Bottom Navigation_24": 4,
    "Bottom Navigation_25": 21,
    "Bottom Navigation_26": 9,
    "Bottom Navigation_27": 4,
    "Bottom Navigation_29": 4,
    "Bottom Navigation_3": 23,
    "Bottom Navigation_4": 6,
    "Bottom Navigation_5": 21,
    "Bottom Navigation_6": 23,
    "Bottom Navigation_7": 30,
    "Bottom Navigation_8": 4,
    "Bottom Navigation_9": 10,
    "Header Component": 32,
    "Header Component New": 35,
    "Header Component_11": 31,
    "Header Component_12": 12,
    "Header Component_13": 12,
    "Header Component_14": 12,
    "Header Component_15": 12,
    "Header Component_16": 12,
    "Header Component_17": 12,
    "Header Component_18": 12,
    "Header Component_19": 12,
    "Header Component_30": 96,
    "KYCFormTopTab": 33,
    "Primary Order Top Tab": 36,
    "Primary Order Top Tab_2": 37,
    "Side Bar": 28,
    "Side Bar_1": 21,
    "Side Bar_10": 1,
    "Side Bar_11": 1,
    "Side Bar_12": 1,
    "Side Bar_13": 1,
    "Side Bar_14": 1,
    "Side Bar_15": 1,
    "Side Bar_16": 22,
    "Side Bar_17": 1,
    "Side Bar_18": 22,
    "Side Bar_2": 1,
    "Side Bar_3": 1,
    "Side Bar_4": 1,
    "Side Bar_5": 22,
    "Side Bar_6": 1,
    "Side Bar_7": 1,
    "Side Bar_8": 1,
    "Side Bar_9": 1,
    "VisitsInfoTopTab": 34,
    "VisitsInfoTopTab_1": 86,
    "VisitsInfoTopTab_2": 86,
    "VisitsInfoTopTab_3": 86,
    "VisitsInfoTopTab_4": 86,
    "VisitsInfoTopTab_5": 86
  },
  "ControlUniqueIds": {
    "add_1": 395,
    "AddMediaButton1": 259,
    "AddMediaWithImage1": 261,
    "All Orders": 800,
    "App": 1,
    "Bag": 182,
    "Bags": 642,
    "Birth": 278,
    "Bottom Navigation": 3,
    "Bottom Navigation_1": 166,
    "Bottom Navigation_10": 266,
    "Bottom Navigation_11": 648,
    "Bottom Navigation_12": 506,
    "Bottom Navigation_13": 604,
    "Bottom Navigation_14": 545,
    "Bottom Navigation_15": 931,
    "Bottom Navigation_16": 97,
    "Bottom Navigation_17": 705,
    "Bottom Navigation_18": 747,
    "Bottom Navigation_19": 756,
    "Bottom Navigation_2": 228,
    "Bottom Navigation_20": 764,
    "Bottom Navigation_21": 71,
    "Bottom Navigation_22": 560,
    "Bottom Navigation_23": 619,
    "Bottom Navigation_24": 200,
    "Bottom Navigation_25": 798,
    "Bottom Navigation_26": 341,
    "Bottom Navigation_27": 187,
    "Bottom Navigation_29": 662,
    "Bottom Navigation_3": 860,
    "Bottom Navigation_4": 396,
    "Bottom Navigation_5": 897,
    "Bottom Navigation_6": 284,
    "Bottom Navigation_7": 21,
    "Bottom Navigation_8": 300,
    "Bottom Navigation_9": 444,
    "Button1": 207,
    "Button1_1": 173,
    "Button1_2": 234,
    "Button1_3": 208,
    "Button1_4": 627,
    "Button1_5": 628,
    "Button18_1": 252,
    "Button18_2": 312,
    "Button2": 886,
    "Button2_1": 896,
    "Button2_11": 797,
    "Button2_2": 391,
    "Button2_3": 534,
    "Button2_4": 544,
    "Button2_5": 920,
    "Button2_6": 930,
    "Button2_7": 390,
    "Button2_8": 494,
    "Button2_9": 849,
    "Button3": 603,
    "Button3_1": 602,
    "Button3_15": 263,
    "Button3_2": 704,
    "Button3_3": 703,
    "Button3_4": 746,
    "Button3_5": 745,
    "Button4": 873,
    "Button4_1": 351,
    "Button4_10": 633,
    "Button4_11": 774,
    "Button4_2": 517,
    "Button4_3": 520,
    "Button4_4": 816,
    "Button4_5": 907,
    "Button4_6": 213,
    "Button4_7": 813,
    "Button4_8": 459,
    "Button4_9": 456,
    "Button5": 206,
    "Button5_1": 626,
    "Button5_2": 663,
    "Button5_3": 664,
    "Button6": 820,
    "Button6_1": 464,
    "Button7": 755,
    "Button7_1": 754,
    "Button7_2": 762,
    "Button7_3": 763,
    "Button7_4": 362,
    "Camera2": 265,
    "Camera2_1": 340,
    "Canvas1": 99,
    "Canvas2": 353,
    "Canvas2_1": 241,
    "Canvas2_2": 307,
    "CategoryFilter": 211,
    "CategoryFilter_1": 631,
    "Checkbox2": 659,
    "Circle_1": 394,
    "Circle1_1": 614,
    "Circle1_2": 868,
    "Circle1_3": 769,
    "Circle4": 359,
    "Comp Info": 303,
    "Competitor Info": 250,
    "Competitor Info_1": 262,
    "Complaints": 899,
    "Completed html": 821,
    "Completed html_1": 854,
    "Completed html_15": 877,
    "Completed html_16": 779,
    "Completed html_17": 525,
    "Completed html_18": 911,
    "Completed html_2": 852,
    "Completed html_20": 452,
    "Completed html_21": 463,
    "Completed html_22": 496,
    "Completed html_23": 497,
    "Completed html_24": 498,
    "Completed html_25": 499,
    "Completed html_26": 500,
    "Completed html_3": 853,
    "Completed html_4": 850,
    "Completed html_5": 851,
    "Completed html_6": 806,
    "Completed html_7": 807,
    "Container1": 310,
    "Container1_1": 243,
    "Container1_2": 309,
    "Container2": 258,
    "Customer (Dist)": 864,
    "Customer (Dist) Plan Visit": 509,
    "Customer (Dist)_1": 765,
    "Customer Search": 870,
    "Customer Search_1": 514,
    "Customer Search_2": 904,
    "Customer Search_3": 771,
    "Daily Reports": 124,
    "Dashboard Toptab": 120,
    "Dashboard Toptab_1": 403,
    "DataCard1": 100,
    "DataCard2": 354,
    "DataCard2_1": 242,
    "DataCard2_2": 308,
    "Date Gallery": 518,
    "DatePicker1": 388,
    "DatePicker3_1": 521,
    "day ended": 119,
    "Day Ended": 189,
    "day started": 118,
    "DistLabel_12": 255,
    "DistLabel_13": 257,
    "DistLabel_19": 316,
    "DistLabel_20": 319,
    "DistLabel_21": 321,
    "DistLabel_22": 324,
    "DistLabel_23": 327,
    "DistLabel_24": 329,
    "DistLabel_25": 333,
    "DistLabel_26": 335,
    "DistLabel_27": 337,
    "DistLabel_5": 244,
    "DistLabel_6": 246,
    "DistLabel_7": 248,
    "DistLabel_8": 251,
    "DistLabel_9": 311,
    "Distributor": 491,
    "Distributor_11": 318,
    "Distributor_12": 326,
    "Distributor_13": 334,
    "Distributor_2": 245,
    "Distributor_3": 249,
    "Edit backdrop": 346,
    "Edit form": 399,
    "EditBackdrop": 344,
    "EditModal": 397,
    "End day": 606,
    "filter": 814,
    "Filter": 649,
    "filter_2": 811,
    "filter_3": 457,
    "filter_4": 454,
    "Gallery1_1": 30,
    "Gallery1_10": 35,
    "Gallery1_18": 43,
    "Gallery1_19": 48,
    "Gallery1_2": 175,
    "Gallery1_3": 13,
    "Gallery2": 22,
    "Gallery2_1": 4,
    "Gallery3_1": 874,
    "Gallery3_2": 775,
    "Gallery3_3": 522,
    "Gallery3_4": 908,
    "Gallery3_5": 81,
    "Gallery4": 871,
    "Gallery4_1": 349,
    "Gallery4_2": 515,
    "Gallery4_3": 905,
    "Gallery4_4": 772,
    "Gallery5": 355,
    "Gallery5_1": 583,
    "Gallery5_2": 684,
    "Gallery5_3": 726,
    "Gallery5_4": 407,
    "galleryTemplate1": 216,
    "galleryTemplate1_1": 31,
    "galleryTemplate1_10": 36,
    "galleryTemplate1_18": 44,
    "galleryTemplate1_19": 49,
    "galleryTemplate1_2": 176,
    "galleryTemplate1_3": 14,
    "galleryTemplate1_4": 636,
    "galleryTemplate11": 654,
    "galleryTemplate11_1": 658,
    "galleryTemplate2": 23,
    "galleryTemplate2_1": 5,
    "galleryTemplate2_3": 121,
    "galleryTemplate2_4": 404,
    "galleryTemplate3": 818,
    "galleryTemplate3_1": 875,
    "galleryTemplate3_2": 776,
    "galleryTemplate3_3": 523,
    "galleryTemplate3_4": 909,
    "galleryTemplate3_5": 82,
    "galleryTemplate3_6": 461,
    "galleryTemplate4": 872,
    "galleryTemplate4_1": 350,
    "galleryTemplate4_10": 632,
    "galleryTemplate4_11": 773,
    "galleryTemplate4_2": 516,
    "galleryTemplate4_3": 519,
    "galleryTemplate4_4": 815,
    "galleryTemplate4_5": 906,
    "galleryTemplate4_6": 212,
    "galleryTemplate4_7": 812,
    "galleryTemplate4_8": 458,
    "galleryTemplate4_9": 455,
    "galleryTemplate5": 356,
    "galleryTemplate5_1": 584,
    "galleryTemplate5_2": 685,
    "galleryTemplate5_3": 727,
    "galleryTemplate5_4": 408,
    "Group1": 154,
    "Group1_1": 157,
    "Group10": 862,
    "Group11": 892,
    "Group11_1": 540,
    "Group11_2": 926,
    "Group12": 890,
    "Group12_1": 538,
    "Group12_2": 924,
    "Group12_3": 792,
    "Group13": 891,
    "Group13_1": 539,
    "Group13_2": 925,
    "Group13_3": 793,
    "Group14": 898,
    "Group14_1": 799,
    "Group14_2": 546,
    "Group14_3": 932,
    "Group15": 398,
    "Group15_1": 188,
    "Group15_2": 378,
    "Group15_3": 379,
    "Group15_4": 599,
    "Group15_5": 600,
    "Group15_6": 700,
    "Group15_7": 701,
    "Group15_8": 742,
    "Group15_9": 743,
    "Group16": 314,
    "Group17": 605,
    "Group17_1": 706,
    "Group17_2": 748,
    "Group18": 94,
    "Group19": 95,
    "Group2": 155,
    "Group2_1": 158,
    "Group2_10": 562,
    "Group2_4": 301,
    "Group2_5": 73,
    "Group2_6": 72,
    "Group2_7": 74,
    "Group2_8": 75,
    "Group2_9": 76,
    "Group20": 96,
    "Group22": 445,
    "Group26": 508,
    "Group26_1": 863,
    "Group3": 156,
    "Group3_1": 159,
    "Group3_4": 302,
    "Group3_5": 561,
    "Group3_6": 620,
    "Group3_7": 201,
    "Group4": 841,
    "Group4_1": 621,
    "Group4_3": 484,
    "Group5": 842,
    "Group5_2": 485,
    "Group6": 843,
    "Group6_2": 486,
    "Group7": 861,
    "Group7_2": 507,
    "Group8": 254,
    "Group9": 164,
    "Header Component": 17,
    "Header Component New": 39,
    "Header Component_11": 9,
    "Header Component_12": 238,
    "Header Component_13": 304,
    "Header Component_14": 168,
    "Header Component_15": 564,
    "Header Component_16": 78,
    "Header Component_17": 401,
    "Header Component_18": 666,
    "Header Component_19": 708,
    "Header Component_30": 343,
    "Home": 98,
    "HtmlText1": 217,
    "HtmlText1_1": 218,
    "HtmlText1_10": 125,
    "HtmlText1_100": 723,
    "HtmlText1_101": 766,
    "HtmlText1_102": 777,
    "HtmlText1_103": 783,
    "HtmlText1_104": 784,
    "HtmlText1_105": 785,
    "HtmlText1_11": 135,
    "HtmlText1_12": 126,
    "HtmlText1_13": 134,
    "HtmlText1_14": 127,
    "HtmlText1_15": 136,
    "HtmlText1_16": 101,
    "HtmlText1_17": 104,
    "HtmlText1_18": 203,
    "HtmlText1_19": 802,
    "HtmlText1_2": 819,
    "HtmlText1_20": 145,
    "HtmlText1_21": 143,
    "HtmlText1_22": 144,
    "HtmlText1_23": 107,
    "HtmlText1_24": 623,
    "HtmlText1_25": 117,
    "HtmlText1_26": 116,
    "HtmlText1_27": 637,
    "HtmlText1_28": 638,
    "HtmlText1_3": 824,
    "HtmlText1_34": 448,
    "HtmlText1_35": 83,
    "HtmlText1_36": 85,
    "HtmlText1_37": 86,
    "HtmlText1_38": 87,
    "HtmlText1_39": 462,
    "HtmlText1_4": 825,
    "HtmlText1_40": 466,
    "HtmlText1_41": 467,
    "HtmlText1_42": 468,
    "HtmlText1_43": 475,
    "HtmlText1_44": 476,
    "HtmlText1_45": 286,
    "HtmlText1_46": 290,
    "HtmlText1_47": 53,
    "HtmlText1_48": 55,
    "HtmlText1_49": 548,
    "HtmlText1_5": 823,
    "HtmlText1_50": 550,
    "HtmlText1_51": 607,
    "HtmlText1_52": 609,
    "HtmlText1_53": 190,
    "HtmlText1_54": 192,
    "HtmlText1_55": 477,
    "HtmlText1_57": 374,
    "HtmlText1_58": 375,
    "HtmlText1_59": 567,
    "HtmlText1_6": 833,
    "HtmlText1_60": 177,
    "HtmlText1_61": 178,
    "HtmlText1_62": 587,
    "HtmlText1_63": 594,
    "HtmlText1_64": 595,
    "HtmlText1_65": 865,
    "HtmlText1_66": 568,
    "HtmlText1_67": 573,
    "HtmlText1_68": 575,
    "HtmlText1_69": 578,
    "HtmlText1_7": 834,
    "HtmlText1_70": 580,
    "HtmlText1_71": 876,
    "HtmlText1_72": 883,
    "HtmlText1_73": 882,
    "HtmlText1_74": 688,
    "HtmlText1_75": 695,
    "HtmlText1_76": 696,
    "HtmlText1_77": 668,
    "HtmlText1_78": 669,
    "HtmlText1_79": 674,
    "HtmlText1_8": 832,
    "HtmlText1_80": 676,
    "HtmlText1_81": 679,
    "HtmlText1_82": 900,
    "HtmlText1_83": 910,
    "HtmlText1_84": 916,
    "HtmlText1_85": 917,
    "HtmlText1_86": 268,
    "HtmlText1_87": 681,
    "HtmlText1_88": 730,
    "HtmlText1_89": 737,
    "HtmlText1_9": 40,
    "HtmlText1_90": 738,
    "HtmlText1_91": 710,
    "HtmlText1_92": 711,
    "HtmlText1_93": 716,
    "HtmlText1_94": 510,
    "HtmlText1_95": 524,
    "HtmlText1_96": 530,
    "HtmlText1_97": 531,
    "HtmlText1_98": 718,
    "HtmlText1_99": 721,
    "HtmlText2_1": 295,
    "HtmlText2_10": 617,
    "HtmlText2_12": 198,
    "HtmlText2_2": 298,
    "HtmlText2_3": 60,
    "HtmlText2_4": 62,
    "HtmlText2_5": 65,
    "HtmlText2_6": 67,
    "HtmlText2_7": 69,
    "HtmlText2_8": 555,
    "HtmlText2_9": 558,
    "HtmlText4_1": 18,
    "Icon1": 28,
    "Icon1_1": 24,
    "Icon1_12": 360,
    "Icon1_13": 363,
    "Icon1_2": 7,
    "Icon10": 894,
    "Icon10_1": 382,
    "Icon10_2": 542,
    "Icon10_3": 928,
    "Icon10_4": 383,
    "Icon10_5": 488,
    "Icon10_6": 845,
    "Icon10_7": 795,
    "Icon11": 880,
    "Icon11_1": 528,
    "Icon11_2": 914,
    "Icon11_3": 781,
    "Icon12": 348,
    "Icon12_1": 171,
    "Icon13": 887,
    "Icon13_1": 535,
    "Icon13_2": 921,
    "Icon14": 239,
    "Icon14_1": 169,
    "Icon14_2": 565,
    "Icon14_3": 79,
    "Icon14_4": 305,
    "Icon14_5": 402,
    "Icon14_6": 667,
    "Icon14_7": 709,
    "Icon14_8": 750,
    "Icon14_9": 758,
    "Icon15": 272,
    "Icon16": 279,
    "Icon2": 210,
    "Icon2_1": 103,
    "Icon2_2": 630,
    "Icon2_4": 288,
    "Icon2_5": 174,
    "Icon22_1": 253,
    "Icon22_2": 313,
    "Icon3": 214,
    "Icon3_1": 634,
    "Icon3_2": 652,
    "Icon4": 20,
    "Icon5": 810,
    "Icon6": 209,
    "Icon6_1": 629,
    "Icon6_16": 46,
    "Icon6_17": 51,
    "Icon6_3": 16,
    "Icon7": 41,
    "Icon8": 317,
    "Icon8_1": 325,
    "Icon8_2": 332,
    "Icon9": 588,
    "Icon9_1": 689,
    "Icon9_2": 731,
    "Image1": 102,
    "Image1_1": 106,
    "Image1_10": 195,
    "Image1_11": 289,
    "Image1_6": 293,
    "Image1_7": 58,
    "Image1_8": 553,
    "Image1_9": 612,
    "Image2": 219,
    "Image2_1": 179,
    "Image2_2": 589,
    "Image2_3": 639,
    "Image2_4": 690,
    "Image2_5": 732,
    "Image3": 29,
    "Image4": 230,
    "Image5": 296,
    "Image5_1": 63,
    "Image5_2": 557,
    "Image5_3": 616,
    "Image5_4": 197,
    "Image6": 271,
    "Image7": 751,
    "Image7_1": 759,
    "Info 1": 315,
    "Info 2": 323,
    "Info 3": 331,
    "Items Gallery": 653,
    "KYCFormTopTab": 12,
    "Label1": 220,
    "Label1_1": 640,
    "Label1_2": 180,
    "Label1_3": 878,
    "Label1_4": 146,
    "Label1_5": 912,
    "Label1_6": 651,
    "Label1_7": 778,
    "Label1_8": 84,
    "Label1_9": 526,
    "Label10": 847,
    "Label10_1": 490,
    "Label10_2": 227,
    "Label10_3": 647,
    "Label11": 805,
    "Label11_1": 869,
    "Label11_2": 770,
    "Label11_3": 513,
    "Label11_4": 903,
    "Label11_5": 270,
    "Label11_6": 451,
    "Label12": 495,
    "Label13": 752,
    "Label13_1": 760,
    "Label13_10": 729,
    "Label13_11": 410,
    "Label13_8": 586,
    "Label13_9": 687,
    "Label14": 753,
    "Label14_1": 761,
    "Label15_3": 364,
    "Label19_33": 366,
    "Label19_34": 367,
    "Label19_35": 590,
    "Label19_36": 591,
    "Label19_37": 369,
    "Label19_38": 370,
    "Label19_39": 592,
    "Label19_40": 593,
    "Label19_41": 365,
    "Label19_42": 371,
    "Label19_43": 368,
    "Label19_44": 372,
    "Label19_45": 691,
    "Label19_46": 692,
    "Label19_47": 693,
    "Label19_48": 694,
    "Label19_49": 733,
    "Label19_50": 734,
    "Label19_51": 735,
    "Label19_52": 736,
    "Label19_53": 411,
    "Label19_54": 412,
    "Label19_55": 413,
    "Label19_56": 414,
    "Label2": 225,
    "Label2_1": 645,
    "Label2_10": 829,
    "Label2_100": 481,
    "Label2_101": 482,
    "Label2_102": 483,
    "Label2_103": 501,
    "Label2_104": 502,
    "Label2_105": 503,
    "Label2_106": 504,
    "Label2_107": 505,
    "Label2_11": 830,
    "Label2_111": 527,
    "Label2_112": 529,
    "Label2_113": 532,
    "Label2_114": 533,
    "Label2_115": 536,
    "Label2_116": 537,
    "Label2_12": 831,
    "Label2_13": 822,
    "Label2_14": 836,
    "Label2_15": 837,
    "Label2_16": 835,
    "Label2_17": 838,
    "Label2_18": 131,
    "Label2_19": 128,
    "Label2_2": 223,
    "Label2_20": 132,
    "Label2_21": 129,
    "Label2_22": 133,
    "Label2_23": 130,
    "Label2_24": 142,
    "Label2_25": 137,
    "Label2_26": 140,
    "Label2_27": 138,
    "Label2_28": 141,
    "Label2_29": 139,
    "Label2_3": 224,
    "Label2_30": 8,
    "Label2_31": 147,
    "Label2_32": 150,
    "Label2_33": 151,
    "Label2_34": 148,
    "Label2_35": 149,
    "Label2_36": 152,
    "Label2_37": 641,
    "Label2_38": 233,
    "Label2_39": 88,
    "Label2_4": 226,
    "Label2_40": 89,
    "Label2_41": 90,
    "Label2_42": 91,
    "Label2_43": 92,
    "Label2_44": 93,
    "Label2_45": 232,
    "Label2_46": 236,
    "Label2_47": 235,
    "Label2_48": 123,
    "Label2_49": 406,
    "Label2_5": 221,
    "Label2_50": 643,
    "Label2_51": 644,
    "Label2_52": 646,
    "Label2_57": 181,
    "Label2_58": 183,
    "Label2_59": 184,
    "Label2_6": 25,
    "Label2_60": 185,
    "Label2_61": 186,
    "Label2_62": 879,
    "Label2_63": 884,
    "Label2_64": 780,
    "Label2_65": 885,
    "Label2_66": 888,
    "Label2_67": 786,
    "Label2_68": 889,
    "Label2_69": 465,
    "Label2_7": 826,
    "Label2_70": 469,
    "Label2_71": 470,
    "Label2_72": 881,
    "Label2_73": 471,
    "Label2_74": 839,
    "Label2_75": 840,
    "Label2_76": 859,
    "Label2_77": 857,
    "Label2_78": 858,
    "Label2_79": 855,
    "Label2_8": 827,
    "Label2_80": 856,
    "Label2_81": 782,
    "Label2_82": 787,
    "Label2_83": 789,
    "Label2_84": 790,
    "Label2_85": 788,
    "Label2_86": 791,
    "Label2_88": 472,
    "Label2_89": 473,
    "Label2_9": 828,
    "Label2_90": 474,
    "Label2_91": 478,
    "Label2_92": 479,
    "Label2_93": 913,
    "Label2_94": 915,
    "Label2_95": 918,
    "Label2_96": 919,
    "Label2_97": 922,
    "Label2_98": 923,
    "Label2_99": 480,
    "Label22": 808,
    "Label22_1": 809,
    "Label22_5": 453,
    "Label3": 205,
    "Label3_1": 231,
    "Label3_11": 292,
    "Label3_12": 294,
    "Label3_13": 291,
    "Label3_14": 297,
    "Label3_15": 299,
    "Label3_16": 57,
    "Label3_17": 59,
    "Label3_18": 56,
    "Label3_19": 61,
    "Label3_2": 105,
    "Label3_20": 64,
    "Label3_21": 66,
    "Label3_22": 68,
    "Label3_23": 70,
    "Label3_24": 551,
    "Label3_25": 552,
    "Label3_26": 554,
    "Label3_27": 556,
    "Label3_28": 559,
    "Label3_29": 610,
    "Label3_3": 109,
    "Label3_30": 611,
    "Label3_31": 613,
    "Label3_32": 618,
    "Label3_33": 193,
    "Label3_34": 194,
    "Label3_35": 196,
    "Label3_36": 199,
    "Label3_4": 108,
    "Label3_5": 625,
    "Label36": 361,
    "Label4": 601,
    "Label4_1": 702,
    "Label4_10": 111,
    "Label4_11": 699,
    "Label4_12": 114,
    "Label4_13": 740,
    "Label4_14": 115,
    "Label4_15": 741,
    "Label4_2": 376,
    "Label4_3": 377,
    "Label4_32": 570,
    "Label4_33": 572,
    "Label4_34": 574,
    "Label4_35": 579,
    "Label4_36": 582,
    "Label4_37": 655,
    "Label4_38": 569,
    "Label4_39": 571,
    "Label4_4": 744,
    "Label4_40": 576,
    "Label4_41": 577,
    "Label4_42": 581,
    "Label4_43": 660,
    "Label4_44": 671,
    "Label4_45": 670,
    "Label4_46": 673,
    "Label4_47": 672,
    "Label4_48": 675,
    "Label4_49": 677,
    "Label4_50": 680,
    "Label4_51": 678,
    "Label4_52": 683,
    "Label4_53": 682,
    "Label4_54": 713,
    "Label4_55": 712,
    "Label4_56": 715,
    "Label4_57": 714,
    "Label4_58": 717,
    "Label4_59": 719,
    "Label4_6": 597,
    "Label4_60": 722,
    "Label4_61": 720,
    "Label4_62": 725,
    "Label4_63": 724,
    "Label4_7": 598,
    "Label4_8": 110,
    "Label4_9": 698,
    "Label5": 32,
    "Label5_23": 415,
    "Label5_24": 417,
    "Label5_26": 418,
    "Label5_27": 421,
    "Label5_28": 422,
    "Label5_29": 425,
    "Label5_30": 426,
    "Label5_31": 429,
    "Label5_32": 430,
    "Label5_33": 433,
    "Label5_34": 434,
    "Label5_35": 437,
    "Label5_36": 438,
    "Label5_52": 442,
    "Label5_54": 441,
    "Label5_56": 443,
    "Label6": 19,
    "Label6_1": 11,
    "Label6_2": 615,
    "Label7": 895,
    "Label7_1": 386,
    "Label7_2": 543,
    "Label7_3": 929,
    "Label7_4": 489,
    "Label7_5": 492,
    "Label7_6": 846,
    "Label7_7": 796,
    "Label8": 384,
    "Label8_1": 385,
    "Label8_10": 38,
    "Label8_18": 45,
    "Label8_19": 50,
    "Label8_2": 387,
    "Label8_3": 15,
    "Label8_4": 389,
    "Label9": 273,
    "Label9_1": 275,
    "Label9_2": 277,
    "Label9_3": 280,
    "Label9_4": 282,
    "My Details": 163,
    "name": 358,
    "Order Info": 400,
    "Orders": 817,
    "Orders_1": 460,
    "Planned_1": 393,
    "PowerBI1_2": 162,
    "PowerBI3": 153,
    "PowerBI3_2": 161,
    "Primary Cart": 707,
    "Primary Order Success": 749,
    "Primary Order Top Tab": 42,
    "Primary Order Top Tab_2": 47,
    "Primary Products": 202,
    "Product Gallery": 215,
    "Product Gallery_1": 635,
    "Profile": 267,
    "Rectangle1": 27,
    "Rectangle10": 10,
    "Rectangle11": 656,
    "Rectangle11_1": 661,
    "Rectangle2": 33,
    "Rectangle3": 6,
    "Rectangle3_2": 122,
    "Rectangle3_3": 405,
    "Rectangle4": 357,
    "Rectangle4_1": 585,
    "Rectangle4_2": 686,
    "Rectangle4_3": 728,
    "Rectangle4_4": 409,
    "Rectangle5": 866,
    "Rectangle5_1": 767,
    "Rectangle5_2": 511,
    "Rectangle5_3": 902,
    "Rectangle5_4": 450,
    "Rectangle5_5": 804,
    "Rectangle6": 37,
    "Rectangle7": 893,
    "Rectangle7_1": 380,
    "Rectangle7_2": 541,
    "Rectangle7_3": 927,
    "Rectangle7_4": 381,
    "Rectangle7_5": 487,
    "Rectangle7_6": 844,
    "Rectangle7_7": 794,
    "Rectangle9": 650,
    "Rectangle9_1": 373,
    "Retailer": 493,
    "Retailer_1": 848,
    "Search": 170,
    "Secondary Cart": 665,
    "Secondary Order Success": 757,
    "Secondary Orders": 446,
    "Secondary Products": 622,
    "Select Day Type": 52,
    "Side Bar": 26,
    "Side Bar_1": 345,
    "Side Bar_10": 608,
    "Side Bar_11": 191,
    "Side Bar_12": 867,
    "Side Bar_13": 447,
    "Side Bar_14": 901,
    "Side Bar_15": 512,
    "Side Bar_16": 803,
    "Side Bar_17": 768,
    "Side Bar_18": 449,
    "Side Bar_2": 165,
    "Side Bar_3": 204,
    "Side Bar_4": 801,
    "Side Bar_5": 269,
    "Side Bar_6": 624,
    "Side Bar_7": 287,
    "Side Bar_8": 54,
    "Side Bar_9": 549,
    "Start Screen": 229,
    "Start visit": 237,
    "StartDay": 285,
    "SubItems Gallery": 657,
    "Submit Day": 547,
    "Targets": 160,
    "TextInput1": 222,
    "TextInput2": 274,
    "TextInput2_1": 276,
    "TextInput2_10": 427,
    "TextInput2_11": 428,
    "TextInput2_12": 431,
    "TextInput2_13": 432,
    "TextInput2_14": 435,
    "TextInput2_15": 436,
    "TextInput2_16": 439,
    "TextInput2_17": 440,
    "TextInput2_2": 416,
    "TextInput2_3": 281,
    "TextInput2_4": 283,
    "TextInput2_6": 419,
    "TextInput2_7": 420,
    "TextInput2_8": 423,
    "TextInput2_9": 424,
    "TextInput5": 596,
    "TextInput5_1": 697,
    "TextInput5_2": 739,
    "TextInput7": 247,
    "TextInput7_3": 256,
    "TextInput7_4": 320,
    "TextInput7_5": 322,
    "TextInput7_6": 328,
    "TextInput7_7": 330,
    "TextInput7_8": 336,
    "TextInput7_9": 338,
    "Toggle1": 264,
    "Toggle1_1": 339,
    "total hours": 112,
    "Type": 113,
    "Unplanned_1": 392,
    "UploadedImage1": 260,
    "Visit Cart": 563,
    "Visit DatePicker": 352,
    "Visit History": 77,
    "Visit Products": 167,
    "Visit Search": 347,
    "Visits": 342,
    "VisitsInfoTopTab": 34,
    "VisitsInfoTopTab_1": 240,
    "VisitsInfoTopTab_2": 306,
    "VisitsInfoTopTab_3": 172,
    "VisitsInfoTopTab_4": 566,
    "VisitsInfoTopTab_5": 80
  },
  "FunctionParamsInvariantScripts": {},
  "FunctionParamsInvariantScriptsOnInstances": {},
  "HeaderLastSavedDateTimeUTC": "06/14/2022 06:39:09",
  "IsLegacyComponentAllowGlobalScopeCase": false,
  "LocalConnectionIDReferences": {
    "c9c4816a-4020-432d-9280-92907bb120b2": "\"/providers/microsoft.powerapps/apis/shared_office365users/connections/3d3303b9c30543d884499e3c24ffb277\""
  },
  "LocalDatabaseReferencesAsEmpty": false,
  "LocalResourceFileNames": {
    "accept": "19a92cac-0ba9-4097-9591-08f57d5ac38c.png",
    "ad": "45a97f5b-05c7-453d-98f6-fead352cdb85.png",
    "emp": "1270cf01-8400-445c-aa32-c840dc7257f7.jpg",
    "WhatsApp Image 2022-05-13 at 1.06.35 PM": "f973f2a8-d0f1-4583-81ef-465bdd5338af.jpeg",
    "zoxima logo": "15d2dfa3-42f0-4e20-8784-d4fa4bc51419.png",
    "zoxima logo only": "bbb43c3b-5be3-42ef-80f7-a9ce720451e7.png",
    "ZOXIMALOGO-removebg-preview": "71aa4520-a0b7-4623-8c08-a477cfb76a43.png"
  },
  "LocalResourceRootPaths": {
    "accept": "https://docserverpwaprodsin.blob.core.windows.net/2ec0f25d-c960-436c-a150-05fb9397dab2-1/resource/Assets0Images019a92cac-0ba9-4097-9591-08f57d5ac38c.png?sv=2017-04-17&sr=b&sig=WXrLwJOO2egojkYsNL%2BAcz0RwC7GS10T9JjhlOQTuoQ%3D&spr=https&se=2022-06-15T05%3A59%3A40Z&sp=r",
    "ad": "https://docserverpwaprodsin.blob.core.windows.net/2ec0f25d-c960-436c-a150-05fb9397dab2-1/resource/Assets0Images045a97f5b-05c7-453d-98f6-fead352cdb85.png?sv=2017-04-17&sr=b&sig=BfLhnHrBUMgKGS69bfL423Mm1SNsOnkOQkrnxQFlt34%3D&spr=https&se=2022-06-15T05%3A59%3A40Z&sp=r",
    "emp": "https://docserverpwaprodsin.blob.core.windows.net/2ec0f25d-c960-436c-a150-05fb9397dab2-1/resource/Assets0Images01270cf01-8400-445c-aa32-c840dc7257f7.jpg?sv=2017-04-17&sr=b&sig=hVLDxIYKSRbjil9wfH9T%2FK9xwtn4E0ipniI%2BXD6s1Vo%3D&spr=https&se=2022-06-15T05%3A59%3A40Z&sp=r",
    "WhatsApp Image 2022-05-13 at 1.06.35 PM": "https://docserverpwaprodsin.blob.core.windows.net/2ec0f25d-c960-436c-a150-05fb9397dab2-1/resource/Assets0Images0f973f2a8-d0f1-4583-81ef-465bdd5338af.jpeg?sv=2017-04-17&sr=b&sig=Ekn0fjbknKwj2cIlJIAAROmSfmucmHhXi101kf%2FU%2B0Y%3D&spr=https&se=2022-06-15T05%3A59%3A40Z&sp=r",
    "zoxima logo": "https://docserverpwaprodsin.blob.core.windows.net/2ec0f25d-c960-436c-a150-05fb9397dab2-1/resource/Assets0Images015d2dfa3-42f0-4e20-8784-d4fa4bc51419.png?sv=2017-04-17&sr=b&sig=b%2FtmG%2BfZ48D5z0IH8TLRpfoY82Kr0RixC9btMoP3Kk8%3D&spr=https&se=2022-06-15T05%3A59%3A40Z&sp=r",
    "zoxima logo only": "https://docserverpwaprodsin.blob.core.windows.net/2ec0f25d-c960-436c-a150-05fb9397dab2-1/resource/Assets0Images0bbb43c3b-5be3-42ef-80f7-a9ce720451e7.png?sv=2017-04-17&sr=b&sig=OgAb1dnNmWi6UKhoma7X%2F6t2rlOf0UgWLjsHxEHJE8U%3D&spr=https&se=2022-06-15T05%3A59%3A40Z&sp=r",
    "ZOXIMALOGO-removebg-preview": "https://docserverpwaprodsin.blob.core.windows.net/2ec0f25d-c960-436c-a150-05fb9397dab2-1/resource/Assets0Images071aa4520-a0b7-4623-8c08-a477cfb76a43.png?sv=2017-04-17&sr=b&sig=%2B3XUWjXak8L9vxnUe49ZWZuxg8y7vgzkVPSteRE3viM%3D&spr=https&se=2022-06-15T05%3A59%3A40Z&sp=r"
  },
  "OldLogoFileName": "rcztex3i.jpg",
  "OrderComponentMetadata": {
    "298070d65dca4e3f9856e3d7dc529de0": 1,
    "30f86cc461bf48c695db5dfb932258e8": 7,
    "437f38a1c07644d28e03469a5b5ea640": 4,
    "45a728bf04444425ae2709bcd70ab8ba": 2,
    "48f9900d8e8f467da1e2aba0c74d22a6": 9,
    "51e914e59967428fb6455a4e2470627a": 8,
    "69894502ba10475d874bab19096f81b6": 5,
    "b84e901362bb426a9025d47db36cd790": 0,
    "c24c8cdda8aa4592a2c19c5f7e216f34": 6,
    "c3cb5069657d462d988b819d87f57351": 3
  },
  "OrderComponentTemplate": {
    "298070d65dca4e3f9856e3d7dc529de0": 1,
    "30f86cc461bf48c695db5dfb932258e8": 7,
    "437f38a1c07644d28e03469a5b5ea640": 4,
    "45a728bf04444425ae2709bcd70ab8ba": 2,
    "48f9900d8e8f467da1e2aba0c74d22a6": 9,
    "51e914e59967428fb6455a4e2470627a": 8,
    "69894502ba10475d874bab19096f81b6": 5,
    "b84e901362bb426a9025d47db36cd790": 0,
    "c24c8cdda8aa4592a2c19c5f7e216f34": 6,
    "c3cb5069657d462d988b819d87f57351": 3
  },
  "OrderDataSource": {
    "43b0dc67-68af-47ae-9a9c-9e69d396ba3e": 112,
    "Accounts": 104,
    "Accounts\\account_accountcategorycode": 35,
    "Accounts\\account_accountclassificationcode": 29,
    "Accounts\\account_accountratingcode": 22,
    "Accounts\\account_address1_addresstypecode": 27,
    "Accounts\\account_address1_freighttermscode": 21,
    "Accounts\\account_address1_shippingmethodcode": 20,
    "Accounts\\account_address2_addresstypecode": 34,
    "Accounts\\account_address2_freighttermscode": 26,
    "Accounts\\account_address2_shippingmethodcode": 37,
    "Accounts\\account_businesstypecode": 31,
    "Accounts\\account_creditonhold": 7,
    "Accounts\\account_customersizecode": 24,
    "Accounts\\account_customertypecode": 36,
    "Accounts\\account_donotbulkemail": 10,
    "Accounts\\account_donotbulkpostalmail": 8,
    "Accounts\\account_donotemail": 13,
    "Accounts\\account_donotfax": 11,
    "Accounts\\account_donotphone": 17,
    "Accounts\\account_donotpostalmail": 12,
    "Accounts\\account_donotsendmm": 6,
    "Accounts\\account_followemail": 15,
    "Accounts\\account_industrycode": 30,
    "Accounts\\account_isprivate": 9,
    "Accounts\\account_marketingonly": 14,
    "Accounts\\account_merged": 16,
    "Accounts\\account_ownershipcode": 25,
    "Accounts\\account_participatesinworkflow": 18,
    "Accounts\\account_paymenttermscode": 32,
    "Accounts\\account_preferredappointmentdaycode": 38,
    "Accounts\\account_preferredappointmenttimecode": 23,
    "Accounts\\account_preferredcontactmethodcode": 28,
    "Accounts\\account_shippingmethodcode": 39,
    "Accounts\\account_statecode": 41,
    "Accounts\\account_statuscode": 42,
    "Accounts\\account_territorycode": 40,
    "Accounts\\cr431_account_cr431_accounttype": 33,
    "Accounts\\cr431_account_cr431_active": 19,
    "Accounts\\default.cds_account_views": 91,
    "AllProducts": 119,
    "Attendance": 113,
    "Attendences": 105,
    "Attendences\\cr431_attendence_cr431_type": 46,
    "Attendences\\cr431_attendence_statecode": 47,
    "Attendences\\cr431_attendence_statuscode": 48,
    "Attendences\\cr431_endday_cr431_attendence": 44,
    "Attendences\\cr431_start_cr431_attendence": 43,
    "Attendences\\cr431_startday_cr431_attendence": 45,
    "Attendences\\default.cds_cr431_attendence_views": 92,
    "Categories": 108,
    "Categories\\cr431_category_statecode": 78,
    "Categories\\cr431_category_statuscode": 79,
    "Categories\\default.cds_cr431_category_views": 95,
    "colMyAccounts": 126,
    "ComboBoxSample": 101,
    "CreateItemsRecord": 120,
    "CreateOrderRecord": 129,
    "CustomGallerySample": 99,
    "DropDownSample": 102,
    "FilterList": 118,
    "ImageCol": 114,
    "NewVisit": 123,
    "Office365Users": 0,
    "OfflinePriceList": 127,
    "OfflineProducts": 125,
    "OfflineSalesHeader": 130,
    "OfflineSalesOrderLines": 128,
    "OfflineVisits": 122,
    "Order Line": 111,
    "Order Line\\cr431_orderline_cr431_uom": 86,
    "Order Line\\cr431_orderline_statecode": 87,
    "Order Line\\cr431_orderline_statuscode": 88,
    "Order Line\\default.cds_cr431_orderline_views": 98,
    "PrimaryCart": 115,
    "Product Items": 109,
    "Product Items\\cr431_productitem_statecode": 80,
    "Product Items\\cr431_productitem_statuscode": 81,
    "Product Items\\default.cds_cr431_productitem_views": 96,
    "Product Price List": 110,
    "Product Price List\\cr431_productpricelist_cr431_pricetype": 82,
    "Product Price List\\cr431_productpricelist_cr431_pricingcomponent": 83,
    "Product Price List\\cr431_productpricelist_statecode": 84,
    "Product Price List\\cr431_productpricelist_statuscode": 85,
    "Product Price List\\default.cds_cr431_productpricelist_views": 97,
    "RadioSample": 100,
    "Sales Order": 103,
    "Sales Order\\cr431_ordertype": 3,
    "Sales Order\\cr431_salesorder_cr431_cancelledorder": 1,
    "Sales Order\\cr431_salesorder_cr431_orderstatus": 2,
    "Sales Order\\cr431_salesorder_statecode": 4,
    "Sales Order\\cr431_salesorder_statuscode": 5,
    "Sales Order\\default.cds_cr431_salesorder_views": 90,
    "SecondaryCart": 131,
    "SelectedVisitForEdit": 121,
    "SingleVisit": 124,
    "subItems": 116,
    "Users": 106,
    "Users\\cr431_details": 89,
    "Users\\default.cds_systemuser_views": 93,
    "Users\\systemuser_accessmode": 69,
    "Users\\systemuser_address1_addresstypecode": 58,
    "Users\\systemuser_address1_shippingmethodcode": 59,
    "Users\\systemuser_address2_addresstypecode": 71,
    "Users\\systemuser_address2_shippingmethodcode": 72,
    "Users\\systemuser_azurestate": 60,
    "Users\\systemuser_caltype": 70,
    "Users\\systemuser_defaultfilterspopulated": 54,
    "Users\\systemuser_deletestate": 67,
    "Users\\systemuser_displayinserviceviews": 52,
    "Users\\systemuser_emailrouteraccessapproval": 64,
    "Users\\systemuser_incomingemaildeliverymethod": 68,
    "Users\\systemuser_invitestatuscode": 61,
    "Users\\systemuser_isactivedirectoryuser": 51,
    "Users\\systemuser_isdisabled": 53,
    "Users\\systemuser_isemailaddressapprovedbyo365admin": 56,
    "Users\\systemuser_isintegrationuser": 55,
    "Users\\systemuser_isuserlicensed": 50,
    "Users\\systemuser_isusersynced": 57,
    "Users\\systemuser_outgoingemaildeliverymethod": 65,
    "Users\\systemuser_preferredaddresscode": 62,
    "Users\\systemuser_preferredemailcode": 63,
    "Users\\systemuser_preferredphonecode": 66,
    "Users\\systemuser_setupuser": 49,
    "VisitData": 117,
    "Visits_1": 107,
    "Visits_1\\cr431_visit_cr431_locationmatched": 77,
    "Visits_1\\cr431_visit_cr431_status": 73,
    "Visits_1\\cr431_visit_cr431_visittype": 74,
    "Visits_1\\cr431_visit_statecode": 75,
    "Visits_1\\cr431_visit_statuscode": 76,
    "Visits_1\\default.cds_cr431_visit_views": 94
  },
  "OrderGroupControls": {
    "AddMediaWithImage1": {
      "AddMediaButton1": 1,
      "UploadedImage1": 0
    },
    "Edit form": {
      "Button2_7": 1,
      "Icon10_4": 0,
      "Rectangle7_4": 2
    },
    "EditModal": {
      "Button2_2": 2,
      "Icon10_1": 0,
      "Label7_1": 1,
      "Rectangle7_1": 3
    },
    "Group1": {
      "HtmlText1_10": 2,
      "Label2_18": 1,
      "Label2_19": 0
    },
    "Group1_1": {
      "HtmlText1_20": 2,
      "Label2_31": 0,
      "Label2_32": 1
    },
    "Group10": {
      "Completed html_6": 2,
      "Icon5": 0,
      "Label22": 1
    },
    "Group11": {
      "Button2": 1,
      "Icon13": 0
    },
    "Group11_1": {
      "Button2_3": 1,
      "Icon13_1": 0
    },
    "Group11_2": {
      "Button2_5": 1,
      "Icon13_2": 0
    },
    "Group12": {
      "HtmlText1_72": 1,
      "Label2_65": 0,
      "Label2_68": 2
    },
    "Group12_1": {
      "HtmlText1_97": 1,
      "Label2_114": 0,
      "Label2_116": 2
    },
    "Group12_2": {
      "HtmlText1_85": 1,
      "Label2_96": 0,
      "Label2_98": 2
    },
    "Group12_3": {
      "HtmlText1_104": 1,
      "Label2_82": 0,
      "Label2_84": 2
    },
    "Group13": {
      "HtmlText1_73": 2,
      "Label2_63": 1,
      "Label2_66": 0
    },
    "Group13_1": {
      "HtmlText1_96": 2,
      "Label2_113": 1,
      "Label2_115": 0
    },
    "Group13_2": {
      "HtmlText1_84": 2,
      "Label2_95": 1,
      "Label2_97": 0
    },
    "Group13_3": {
      "HtmlText1_103": 2,
      "Label2_67": 1,
      "Label2_83": 0
    },
    "Group14": {
      "Button2_1": 2,
      "Icon10": 0,
      "Label7": 1,
      "Rectangle7": 3
    },
    "Group14_1": {
      "Button2_11": 2,
      "Icon10_7": 0,
      "Label7_7": 1,
      "Rectangle7_7": 3
    },
    "Group14_2": {
      "Button2_4": 2,
      "Icon10_2": 0,
      "Label7_2": 1,
      "Rectangle7_2": 3
    },
    "Group14_3": {
      "Button2_6": 2,
      "Icon10_3": 0,
      "Label7_3": 1,
      "Rectangle7_3": 3
    },
    "Group15": {
      "Icon12": 0,
      "Visit Search": 1
    },
    "Group15_1": {
      "Icon12_1": 0,
      "Search": 1
    },
    "Group15_2": {
      "HtmlText1_57": 1,
      "Label4_2": 0
    },
    "Group15_3": {
      "HtmlText1_58": 1,
      "Label4_3": 0
    },
    "Group15_4": {
      "HtmlText1_63": 1,
      "Label4_6": 0
    },
    "Group15_5": {
      "HtmlText1_64": 1,
      "Label4_7": 0
    },
    "Group15_6": {
      "HtmlText1_75": 1,
      "Label4_9": 0
    },
    "Group15_7": {
      "HtmlText1_76": 1,
      "Label4_11": 0
    },
    "Group15_8": {
      "HtmlText1_89": 1,
      "Label4_13": 0
    },
    "Group15_9": {
      "HtmlText1_90": 1,
      "Label4_15": 0
    },
    "Group16": {
      "Button18_2": 1,
      "Icon22_2": 0
    },
    "Group17": {
      "HtmlText1_59": 0,
      "HtmlText1_66": 2,
      "HtmlText1_67": 6,
      "HtmlText1_68": 8,
      "HtmlText1_69": 11,
      "HtmlText1_70": 14,
      "Label4_32": 1,
      "Label4_33": 4,
      "Label4_34": 7,
      "Label4_35": 10,
      "Label4_36": 13,
      "Label4_38": 3,
      "Label4_39": 5,
      "Label4_40": 9,
      "Label4_41": 12,
      "Label4_42": 15
    },
    "Group17_1": {
      "HtmlText1_77": 0,
      "HtmlText1_78": 2,
      "HtmlText1_79": 6,
      "HtmlText1_80": 8,
      "HtmlText1_81": 11,
      "HtmlText1_87": 14,
      "Label4_44": 1,
      "Label4_45": 3,
      "Label4_46": 4,
      "Label4_47": 5,
      "Label4_48": 7,
      "Label4_49": 9,
      "Label4_50": 10,
      "Label4_51": 12,
      "Label4_52": 13,
      "Label4_53": 15
    },
    "Group17_2": {
      "HtmlText1_100": 14,
      "HtmlText1_91": 0,
      "HtmlText1_92": 2,
      "HtmlText1_93": 6,
      "HtmlText1_98": 8,
      "HtmlText1_99": 11,
      "Label4_54": 1,
      "Label4_55": 3,
      "Label4_56": 4,
      "Label4_57": 5,
      "Label4_58": 7,
      "Label4_59": 9,
      "Label4_60": 10,
      "Label4_61": 12,
      "Label4_62": 13,
      "Label4_63": 15
    },
    "Group18": {
      "HtmlText1_37": 1,
      "Label2_39": 0,
      "Label2_42": 2
    },
    "Group19": {
      "HtmlText1_38": 1,
      "Label2_40": 0,
      "Label2_43": 2
    },
    "Group2": {
      "HtmlText1_12": 2,
      "Label2_20": 0,
      "Label2_21": 1
    },
    "Group2_1": {
      "HtmlText1_21": 2,
      "Label2_33": 0,
      "Label2_34": 1
    },
    "Group2_10": {
      "HtmlText2_8": 1,
      "Label3_27": 0
    },
    "Group2_4": {
      "HtmlText2_1": 1,
      "Label3_14": 0
    },
    "Group2_5": {
      "HtmlText2_3": 1,
      "Label3_19": 0
    },
    "Group2_6": {
      "HtmlText2_4": 1,
      "Label3_20": 0
    },
    "Group2_7": {
      "HtmlText2_5": 1,
      "Label3_21": 0
    },
    "Group2_8": {
      "HtmlText2_6": 1,
      "Label3_22": 0
    },
    "Group2_9": {
      "HtmlText2_7": 1,
      "Label3_23": 0
    },
    "Group20": {
      "HtmlText1_36": 1,
      "Label2_41": 0,
      "Label2_44": 2
    },
    "Group22": {
      "Label5_23": 0,
      "Label5_24": 2,
      "Label5_26": 3,
      "Label5_27": 6,
      "Label5_28": 7,
      "Label5_29": 10,
      "Label5_30": 11,
      "Label5_31": 14,
      "Label5_32": 15,
      "Label5_33": 18,
      "Label5_34": 19,
      "Label5_35": 22,
      "Label5_36": 23,
      "Label5_52": 27,
      "Label5_54": 26,
      "Label5_56": 28,
      "TextInput2_10": 12,
      "TextInput2_11": 13,
      "TextInput2_12": 16,
      "TextInput2_13": 17,
      "TextInput2_14": 20,
      "TextInput2_15": 21,
      "TextInput2_16": 24,
      "TextInput2_17": 25,
      "TextInput2_2": 1,
      "TextInput2_6": 4,
      "TextInput2_7": 5,
      "TextInput2_8": 8,
      "TextInput2_9": 9
    },
    "Group26": {
      "Button2_8": 6,
      "Distributor": 3,
      "Icon10_5": 4,
      "Label12": 0,
      "Label7_4": 5,
      "Label7_5": 2,
      "Rectangle7_5": 7,
      "Retailer": 1
    },
    "Group26_1": {
      "Button2_9": 3,
      "Icon10_6": 2,
      "Label7_6": 1,
      "Rectangle7_6": 4,
      "Retailer_1": 0
    },
    "Group3": {
      "HtmlText1_14": 2,
      "Label2_22": 1,
      "Label2_23": 0
    },
    "Group3_1": {
      "HtmlText1_22": 2,
      "Label2_35": 0,
      "Label2_36": 1
    },
    "Group3_4": {
      "HtmlText2_2": 1,
      "Label3_15": 0
    },
    "Group3_5": {
      "HtmlText2_9": 1,
      "Label3_28": 0
    },
    "Group3_6": {
      "HtmlText2_10": 1,
      "Label3_32": 0
    },
    "Group3_7": {
      "HtmlText2_12": 1,
      "Label3_36": 0
    },
    "Group4": {
      "HtmlText1_6": 1,
      "Label2_14": 0,
      "Label2_17": 2
    },
    "Group4_1": {
      "Circle1_1": 1,
      "Label6_2": 0
    },
    "Group4_3": {
      "HtmlText1_44": 1,
      "Label2_100": 2,
      "Label2_92": 0
    },
    "Group5": {
      "HtmlText1_7": 1,
      "Label2_15": 0,
      "Label2_74": 2
    },
    "Group5_2": {
      "HtmlText1_55": 1,
      "Label2_101": 2,
      "Label2_99": 0
    },
    "Group6": {
      "HtmlText1_8": 1,
      "Label2_16": 0,
      "Label2_75": 2
    },
    "Group6_2": {
      "HtmlText1_43": 1,
      "Label2_102": 2,
      "Label2_91": 0
    },
    "Group7": {
      "Completed html_1": 4,
      "Completed html_2": 2,
      "Completed html_3": 3,
      "Completed html_4": 0,
      "Completed html_5": 1,
      "Label2_76": 9,
      "Label2_77": 7,
      "Label2_78": 8,
      "Label2_79": 5,
      "Label2_80": 6
    },
    "Group7_2": {
      "Completed html_22": 0,
      "Completed html_23": 1,
      "Completed html_24": 2,
      "Completed html_25": 3,
      "Completed html_26": 4,
      "Label2_103": 5,
      "Label2_104": 6,
      "Label2_105": 7,
      "Label2_106": 8,
      "Label2_107": 9
    },
    "Group8": {
      "Button18_1": 1,
      "Icon22_1": 0
    },
    "Group9": {
      "day ended": 15,
      "day started": 14,
      "HtmlText1_17": 0,
      "HtmlText1_23": 3,
      "HtmlText1_25": 13,
      "HtmlText1_26": 12,
      "Image1_1": 2,
      "Label3_2": 1,
      "Label3_3": 5,
      "Label3_4": 4,
      "Label4_10": 7,
      "Label4_12": 10,
      "Label4_14": 11,
      "Label4_8": 6,
      "total hours": 8,
      "Type": 9
    }
  },
  "OrderPcfTemplate": {},
  "OrderTemplate": {},
  "OrderXMLTemplate": {
    "addMedia": 12,
    "button": 10,
    "camera": 14,
    "checkbox": 17,
    "circle": 16,
    "combobox": 11,
    "datepicker": 15,
    "fluidGrid": 6,
    "gallery": 4,
    "groupContainer": 7,
    "htmlViewer": 0,
    "icon": 2,
    "image": 3,
    "label": 5,
    "powerbi": 8,
    "rectangle": 1,
    "text": 9,
    "toggleSwitch": 13
  },
  "PublishOrderIndices": {
    "add_1": 390,
    "AddMediaButton1": 476,
    "AddMediaWithImage1": 475,
    "All Orders": 0,
    "App": 0,
    "Bag": 231,
    "Bags": 154,
    "Birth": 846,
    "Bottom Navigation": 0,
    "Bottom Navigation_1": 67,
    "Bottom Navigation_10": 482,
    "Bottom Navigation_11": 160,
    "Bottom Navigation_12": 645,
    "Bottom Navigation_13": 433,
    "Bottom Navigation_14": 783,
    "Bottom Navigation_15": 746,
    "Bottom Navigation_16": 453,
    "Bottom Navigation_17": 134,
    "Bottom Navigation_18": 201,
    "Bottom Navigation_19": 208,
    "Bottom Navigation_2": 93,
    "Bottom Navigation_20": 215,
    "Bottom Navigation_21": 292,
    "Bottom Navigation_22": 307,
    "Bottom Navigation_23": 322,
    "Bottom Navigation_24": 334,
    "Bottom Navigation_25": 713,
    "Bottom Navigation_26": 520,
    "Bottom Navigation_27": 236,
    "Bottom Navigation_29": 249,
    "Bottom Navigation_3": 583,
    "Bottom Navigation_4": 391,
    "Bottom Navigation_5": 679,
    "Bottom Navigation_6": 852,
    "Bottom Navigation_7": 91,
    "Bottom Navigation_8": 268,
    "Bottom Navigation_9": 828,
    "Button1": 72,
    "Button1_1": 222,
    "Button1_2": 833,
    "Button1_3": 73,
    "Button1_4": 139,
    "Button1_5": 140,
    "Button18_1": 468,
    "Button18_2": 491,
    "Button2": 669,
    "Button2_1": 678,
    "Button2_11": 712,
    "Button2_2": 386,
    "Button2_3": 775,
    "Button2_4": 782,
    "Button2_5": 738,
    "Button2_6": 745,
    "Button2_7": 385,
    "Button2_8": 632,
    "Button2_9": 571,
    "Button3": 432,
    "Button3_1": 431,
    "Button3_15": 479,
    "Button3_2": 133,
    "Button3_3": 132,
    "Button3_4": 200,
    "Button3_5": 199,
    "Button4": 654,
    "Button4_1": 344,
    "Button4_10": 145,
    "Button4_11": 689,
    "Button4_2": 755,
    "Button4_3": 758,
    "Button4_4": 537,
    "Button4_5": 722,
    "Button4_6": 78,
    "Button4_7": 534,
    "Button4_8": 596,
    "Button4_9": 593,
    "Button5": 71,
    "Button5_1": 138,
    "Button5_2": 250,
    "Button5_3": 251,
    "Button6": 541,
    "Button6_1": 601,
    "Button7": 207,
    "Button7_1": 206,
    "Button7_2": 213,
    "Button7_3": 214,
    "Button7_4": 355,
    "Camera2": 481,
    "Camera2_1": 519,
    "Canvas1": 0,
    "Canvas2": 346,
    "Canvas2_1": 457,
    "Canvas2_2": 486,
    "CategoryFilter": 76,
    "CategoryFilter_1": 143,
    "Checkbox2": 246,
    "Circle_1": 389,
    "Circle1_1": 317,
    "Circle1_2": 649,
    "Circle1_3": 683,
    "Circle4": 352,
    "Comp Info": 0,
    "Competitor Info": 466,
    "Competitor Info_1": 478,
    "Complaints": 0,
    "Completed html": 542,
    "Completed html_1": 577,
    "Completed html_15": 658,
    "Completed html_16": 694,
    "Completed html_17": 763,
    "Completed html_18": 726,
    "Completed html_2": 575,
    "Completed html_20": 589,
    "Completed html_21": 600,
    "Completed html_22": 635,
    "Completed html_23": 636,
    "Completed html_24": 637,
    "Completed html_25": 638,
    "Completed html_26": 639,
    "Completed html_3": 576,
    "Completed html_4": 573,
    "Completed html_5": 574,
    "Completed html_6": 526,
    "Completed html_7": 528,
    "Container1": 489,
    "Container1_1": 459,
    "Container1_2": 488,
    "Container2": 474,
    "Customer (Dist)": 0,
    "Customer (Dist) Plan Visit": 0,
    "Customer (Dist)_1": 0,
    "Customer Search": 651,
    "Customer Search_1": 751,
    "Customer Search_2": 718,
    "Customer Search_3": 685,
    "Daily Reports": 26,
    "Dashboard Toptab": 22,
    "Dashboard Toptab_1": 787,
    "DataCard1": 1,
    "DataCard2": 347,
    "DataCard2_1": 458,
    "DataCard2_2": 487,
    "Date Gallery": 756,
    "DatePicker1": 383,
    "DatePicker3_1": 759,
    "day ended": 21,
    "Day Ended": 0,
    "day started": 20,
    "DistLabel_12": 471,
    "DistLabel_13": 473,
    "DistLabel_19": 511,
    "DistLabel_20": 514,
    "DistLabel_21": 516,
    "DistLabel_22": 495,
    "DistLabel_23": 498,
    "DistLabel_24": 500,
    "DistLabel_25": 504,
    "DistLabel_26": 506,
    "DistLabel_27": 508,
    "DistLabel_5": 460,
    "DistLabel_6": 462,
    "DistLabel_7": 464,
    "DistLabel_8": 467,
    "DistLabel_9": 490,
    "Distributor": 629,
    "Distributor_11": 513,
    "Distributor_12": 497,
    "Distributor_13": 505,
    "Distributor_2": 461,
    "Distributor_3": 465,
    "Edit backdrop": 338,
    "Edit form": 375,
    "EditBackdrop": 336,
    "EditModal": 376,
    "End day": 0,
    "filter": 535,
    "Filter": 0,
    "filter_2": 532,
    "filter_3": 594,
    "filter_4": 591,
    "Gallery1_1": 856,
    "Gallery1_10": 878,
    "Gallery1_18": 884,
    "Gallery1_19": 888,
    "Gallery1_2": 224,
    "Gallery1_3": 874,
    "Gallery2": 865,
    "Gallery2_1": 860,
    "Gallery3_1": 655,
    "Gallery3_2": 690,
    "Gallery3_3": 760,
    "Gallery3_4": 723,
    "Gallery3_5": 437,
    "Gallery4": 652,
    "Gallery4_1": 342,
    "Gallery4_2": 753,
    "Gallery4_3": 720,
    "Gallery4_4": 687,
    "Gallery5": 348,
    "Gallery5_1": 412,
    "Gallery5_2": 113,
    "Gallery5_3": 180,
    "Gallery5_4": 791,
    "galleryTemplate1": 81,
    "galleryTemplate1_1": 857,
    "galleryTemplate1_10": 879,
    "galleryTemplate1_18": 885,
    "galleryTemplate1_19": 889,
    "galleryTemplate1_2": 225,
    "galleryTemplate1_3": 875,
    "galleryTemplate1_4": 148,
    "galleryTemplate11": 241,
    "galleryTemplate11_1": 245,
    "galleryTemplate2": 866,
    "galleryTemplate2_1": 861,
    "galleryTemplate2_3": 23,
    "galleryTemplate2_4": 788,
    "galleryTemplate3": 539,
    "galleryTemplate3_1": 656,
    "galleryTemplate3_2": 691,
    "galleryTemplate3_3": 761,
    "galleryTemplate3_4": 724,
    "galleryTemplate3_5": 438,
    "galleryTemplate3_6": 598,
    "galleryTemplate4": 653,
    "galleryTemplate4_1": 343,
    "galleryTemplate4_10": 144,
    "galleryTemplate4_11": 688,
    "galleryTemplate4_2": 754,
    "galleryTemplate4_3": 757,
    "galleryTemplate4_4": 536,
    "galleryTemplate4_5": 721,
    "galleryTemplate4_6": 77,
    "galleryTemplate4_7": 533,
    "galleryTemplate4_8": 595,
    "galleryTemplate4_9": 592,
    "galleryTemplate5": 349,
    "galleryTemplate5_1": 413,
    "galleryTemplate5_2": 114,
    "galleryTemplate5_3": 183,
    "galleryTemplate5_4": 792,
    "Group1": 28,
    "Group1_1": 53,
    "Group10": 527,
    "Group11": 670,
    "Group11_1": 769,
    "Group11_2": 732,
    "Group12": 666,
    "Group12_1": 767,
    "Group12_2": 730,
    "Group12_3": 697,
    "Group13": 664,
    "Group13_1": 768,
    "Group13_2": 731,
    "Group13_3": 698,
    "Group14": 675,
    "Group14_1": 686,
    "Group14_2": 752,
    "Group14_3": 719,
    "Group15": 340,
    "Group15_1": 220,
    "Group15_2": 368,
    "Group15_3": 370,
    "Group15_4": 424,
    "Group15_5": 426,
    "Group15_6": 125,
    "Group15_7": 127,
    "Group15_8": 182,
    "Group15_9": 181,
    "Group16": 492,
    "Group17": 396,
    "Group17_1": 97,
    "Group17_2": 163,
    "Group18": 441,
    "Group19": 442,
    "Group2": 30,
    "Group2_1": 49,
    "Group2_10": 293,
    "Group2_4": 252,
    "Group2_5": 269,
    "Group2_6": 270,
    "Group2_7": 271,
    "Group2_8": 272,
    "Group2_9": 273,
    "Group20": 443,
    "Group22": 786,
    "Group26": 625,
    "Group26_1": 566,
    "Group3": 32,
    "Group3_1": 51,
    "Group3_4": 253,
    "Group3_5": 294,
    "Group3_6": 308,
    "Group3_7": 323,
    "Group4": 544,
    "Group4_1": 309,
    "Group4_3": 615,
    "Group5": 545,
    "Group5_2": 617,
    "Group6": 546,
    "Group6_2": 613,
    "Group7": 572,
    "Group7_2": 634,
    "Group8": 470,
    "Group9": 6,
    "Header Component": 1255,
    "Header Component New": 403,
    "Header Component_11": 67,
    "Header Component_12": 454,
    "Header Component_13": 483,
    "Header Component_14": 216,
    "Header Component_15": 392,
    "Header Component_16": 434,
    "Header Component_17": 784,
    "Header Component_18": 94,
    "Header Component_19": 161,
    "Header Component_30": 335,
    "Home": 0,
    "HtmlText1": 82,
    "HtmlText1_1": 83,
    "HtmlText1_10": 27,
    "HtmlText1_100": 177,
    "HtmlText1_101": 680,
    "HtmlText1_102": 692,
    "HtmlText1_103": 700,
    "HtmlText1_104": 701,
    "HtmlText1_105": 702,
    "HtmlText1_11": 40,
    "HtmlText1_12": 29,
    "HtmlText1_13": 39,
    "HtmlText1_14": 31,
    "HtmlText1_15": 41,
    "HtmlText1_16": 2,
    "HtmlText1_17": 5,
    "HtmlText1_18": 68,
    "HtmlText1_19": 522,
    "HtmlText1_2": 540,
    "HtmlText1_20": 52,
    "HtmlText1_21": 48,
    "HtmlText1_22": 50,
    "HtmlText1_23": 9,
    "HtmlText1_24": 135,
    "HtmlText1_25": 19,
    "HtmlText1_26": 18,
    "HtmlText1_27": 149,
    "HtmlText1_28": 150,
    "HtmlText1_3": 548,
    "HtmlText1_34": 585,
    "HtmlText1_35": 439,
    "HtmlText1_36": 444,
    "HtmlText1_37": 445,
    "HtmlText1_38": 446,
    "HtmlText1_39": 599,
    "HtmlText1_4": 549,
    "HtmlText1_40": 603,
    "HtmlText1_41": 604,
    "HtmlText1_42": 605,
    "HtmlText1_43": 612,
    "HtmlText1_44": 614,
    "HtmlText1_45": 254,
    "HtmlText1_46": 258,
    "HtmlText1_47": 274,
    "HtmlText1_48": 276,
    "HtmlText1_49": 295,
    "HtmlText1_5": 547,
    "HtmlText1_50": 297,
    "HtmlText1_51": 310,
    "HtmlText1_52": 312,
    "HtmlText1_53": 324,
    "HtmlText1_54": 326,
    "HtmlText1_55": 616,
    "HtmlText1_57": 367,
    "HtmlText1_58": 369,
    "HtmlText1_59": 395,
    "HtmlText1_6": 557,
    "HtmlText1_60": 226,
    "HtmlText1_61": 227,
    "HtmlText1_62": 416,
    "HtmlText1_63": 423,
    "HtmlText1_64": 425,
    "HtmlText1_65": 646,
    "HtmlText1_66": 397,
    "HtmlText1_67": 402,
    "HtmlText1_68": 404,
    "HtmlText1_69": 407,
    "HtmlText1_7": 558,
    "HtmlText1_70": 409,
    "HtmlText1_71": 657,
    "HtmlText1_72": 665,
    "HtmlText1_73": 663,
    "HtmlText1_74": 117,
    "HtmlText1_75": 124,
    "HtmlText1_76": 126,
    "HtmlText1_77": 96,
    "HtmlText1_78": 98,
    "HtmlText1_79": 103,
    "HtmlText1_8": 556,
    "HtmlText1_80": 105,
    "HtmlText1_81": 108,
    "HtmlText1_82": 714,
    "HtmlText1_83": 725,
    "HtmlText1_84": 734,
    "HtmlText1_85": 735,
    "HtmlText1_86": 836,
    "HtmlText1_87": 110,
    "HtmlText1_88": 186,
    "HtmlText1_89": 193,
    "HtmlText1_9": 882,
    "HtmlText1_90": 194,
    "HtmlText1_91": 164,
    "HtmlText1_92": 165,
    "HtmlText1_93": 170,
    "HtmlText1_94": 747,
    "HtmlText1_95": 762,
    "HtmlText1_96": 771,
    "HtmlText1_97": 772,
    "HtmlText1_98": 172,
    "HtmlText1_99": 175,
    "HtmlText2_1": 263,
    "HtmlText2_10": 320,
    "HtmlText2_12": 332,
    "HtmlText2_2": 266,
    "HtmlText2_3": 281,
    "HtmlText2_4": 283,
    "HtmlText2_5": 286,
    "HtmlText2_6": 288,
    "HtmlText2_7": 290,
    "HtmlText2_8": 302,
    "HtmlText2_9": 305,
    "HtmlText4_1": 871,
    "Icon1": 854,
    "Icon1_1": 867,
    "Icon1_12": 353,
    "Icon1_13": 356,
    "Icon1_2": 863,
    "Icon10": 676,
    "Icon10_1": 377,
    "Icon10_2": 780,
    "Icon10_3": 743,
    "Icon10_4": 378,
    "Icon10_5": 626,
    "Icon10_6": 567,
    "Icon10_7": 710,
    "Icon11": 661,
    "Icon11_1": 766,
    "Icon11_2": 729,
    "Icon11_3": 696,
    "Icon12": 341,
    "Icon12_1": 219,
    "Icon13": 671,
    "Icon13_1": 776,
    "Icon13_2": 739,
    "Icon14": 455,
    "Icon14_1": 217,
    "Icon14_2": 393,
    "Icon14_3": 435,
    "Icon14_4": 484,
    "Icon14_5": 785,
    "Icon14_6": 95,
    "Icon14_7": 162,
    "Icon14_8": 202,
    "Icon14_9": 209,
    "Icon15": 840,
    "Icon16": 847,
    "Icon2": 75,
    "Icon2_1": 4,
    "Icon2_2": 142,
    "Icon2_4": 256,
    "Icon2_5": 223,
    "Icon22_1": 469,
    "Icon22_2": 493,
    "Icon3": 79,
    "Icon3_1": 146,
    "Icon3_2": 239,
    "Icon4": 873,
    "Icon5": 531,
    "Icon6": 74,
    "Icon6_1": 141,
    "Icon6_16": 887,
    "Icon6_17": 891,
    "Icon6_3": 877,
    "Icon7": 883,
    "Icon8": 512,
    "Icon8_1": 496,
    "Icon8_2": 503,
    "Icon9": 417,
    "Icon9_1": 118,
    "Icon9_2": 187,
    "Image1": 3,
    "Image1_1": 8,
    "Image1_10": 329,
    "Image1_11": 257,
    "Image1_6": 261,
    "Image1_7": 279,
    "Image1_8": 300,
    "Image1_9": 315,
    "Image2": 84,
    "Image2_1": 228,
    "Image2_2": 418,
    "Image2_3": 151,
    "Image2_4": 119,
    "Image2_5": 188,
    "Image3": 855,
    "Image4": 829,
    "Image5": 264,
    "Image5_1": 284,
    "Image5_2": 304,
    "Image5_3": 319,
    "Image5_4": 331,
    "Image6": 839,
    "Image7": 203,
    "Image7_1": 210,
    "Info 1": 510,
    "Info 2": 494,
    "Info 3": 502,
    "Items Gallery": 240,
    "KYCFormTopTab": 1257,
    "Label1": 85,
    "Label1_1": 152,
    "Label1_2": 229,
    "Label1_3": 659,
    "Label1_4": 54,
    "Label1_5": 727,
    "Label1_6": 238,
    "Label1_7": 693,
    "Label1_8": 440,
    "Label1_9": 764,
    "Label10": 569,
    "Label10_1": 628,
    "Label10_2": 92,
    "Label10_3": 159,
    "Label11": 525,
    "Label11_1": 650,
    "Label11_2": 684,
    "Label11_3": 750,
    "Label11_4": 717,
    "Label11_5": 838,
    "Label11_6": 588,
    "Label12": 633,
    "Label13": 204,
    "Label13_1": 211,
    "Label13_10": 185,
    "Label13_11": 794,
    "Label13_8": 415,
    "Label13_9": 116,
    "Label14": 205,
    "Label14_1": 212,
    "Label15_3": 357,
    "Label19_33": 359,
    "Label19_34": 360,
    "Label19_35": 419,
    "Label19_36": 420,
    "Label19_37": 362,
    "Label19_38": 363,
    "Label19_39": 421,
    "Label19_40": 422,
    "Label19_41": 358,
    "Label19_42": 364,
    "Label19_43": 361,
    "Label19_44": 365,
    "Label19_45": 120,
    "Label19_46": 121,
    "Label19_47": 122,
    "Label19_48": 123,
    "Label19_49": 189,
    "Label19_50": 190,
    "Label19_51": 191,
    "Label19_52": 192,
    "Label19_53": 795,
    "Label19_54": 796,
    "Label19_55": 797,
    "Label19_56": 798,
    "Label2": 90,
    "Label2_1": 157,
    "Label2_10": 553,
    "Label2_100": 621,
    "Label2_101": 622,
    "Label2_102": 623,
    "Label2_103": 640,
    "Label2_104": 641,
    "Label2_105": 642,
    "Label2_106": 643,
    "Label2_107": 644,
    "Label2_11": 554,
    "Label2_111": 765,
    "Label2_112": 770,
    "Label2_113": 773,
    "Label2_114": 774,
    "Label2_115": 777,
    "Label2_116": 778,
    "Label2_12": 555,
    "Label2_13": 543,
    "Label2_14": 560,
    "Label2_15": 561,
    "Label2_16": 559,
    "Label2_17": 562,
    "Label2_18": 36,
    "Label2_19": 33,
    "Label2_2": 88,
    "Label2_20": 37,
    "Label2_21": 34,
    "Label2_22": 38,
    "Label2_23": 35,
    "Label2_24": 47,
    "Label2_25": 42,
    "Label2_26": 45,
    "Label2_27": 43,
    "Label2_28": 46,
    "Label2_29": 44,
    "Label2_3": 89,
    "Label2_30": 864,
    "Label2_31": 55,
    "Label2_32": 58,
    "Label2_33": 59,
    "Label2_34": 56,
    "Label2_35": 57,
    "Label2_36": 60,
    "Label2_37": 153,
    "Label2_38": 832,
    "Label2_39": 447,
    "Label2_4": 91,
    "Label2_40": 448,
    "Label2_41": 449,
    "Label2_42": 450,
    "Label2_43": 451,
    "Label2_44": 452,
    "Label2_45": 831,
    "Label2_46": 835,
    "Label2_47": 834,
    "Label2_48": 25,
    "Label2_49": 790,
    "Label2_5": 86,
    "Label2_50": 155,
    "Label2_51": 156,
    "Label2_52": 158,
    "Label2_57": 230,
    "Label2_58": 232,
    "Label2_59": 233,
    "Label2_6": 868,
    "Label2_60": 234,
    "Label2_61": 235,
    "Label2_62": 660,
    "Label2_63": 667,
    "Label2_64": 695,
    "Label2_65": 668,
    "Label2_66": 672,
    "Label2_67": 703,
    "Label2_68": 673,
    "Label2_69": 602,
    "Label2_7": 550,
    "Label2_70": 606,
    "Label2_71": 607,
    "Label2_72": 662,
    "Label2_73": 608,
    "Label2_74": 563,
    "Label2_75": 564,
    "Label2_76": 582,
    "Label2_77": 580,
    "Label2_78": 581,
    "Label2_79": 578,
    "Label2_8": 551,
    "Label2_80": 579,
    "Label2_81": 699,
    "Label2_82": 704,
    "Label2_83": 706,
    "Label2_84": 707,
    "Label2_85": 705,
    "Label2_86": 708,
    "Label2_88": 609,
    "Label2_89": 610,
    "Label2_9": 552,
    "Label2_90": 611,
    "Label2_91": 618,
    "Label2_92": 619,
    "Label2_93": 728,
    "Label2_94": 733,
    "Label2_95": 736,
    "Label2_96": 737,
    "Label2_97": 740,
    "Label2_98": 741,
    "Label2_99": 620,
    "Label22": 529,
    "Label22_1": 530,
    "Label22_5": 590,
    "Label3": 70,
    "Label3_1": 830,
    "Label3_11": 260,
    "Label3_12": 262,
    "Label3_13": 259,
    "Label3_14": 265,
    "Label3_15": 267,
    "Label3_16": 278,
    "Label3_17": 280,
    "Label3_18": 277,
    "Label3_19": 282,
    "Label3_2": 7,
    "Label3_20": 285,
    "Label3_21": 287,
    "Label3_22": 289,
    "Label3_23": 291,
    "Label3_24": 298,
    "Label3_25": 299,
    "Label3_26": 301,
    "Label3_27": 303,
    "Label3_28": 306,
    "Label3_29": 313,
    "Label3_3": 11,
    "Label3_30": 314,
    "Label3_31": 316,
    "Label3_32": 321,
    "Label3_33": 327,
    "Label3_34": 328,
    "Label3_35": 330,
    "Label3_36": 333,
    "Label3_4": 10,
    "Label3_5": 137,
    "Label36": 354,
    "Label4": 430,
    "Label4_1": 131,
    "Label4_10": 13,
    "Label4_11": 130,
    "Label4_12": 16,
    "Label4_13": 196,
    "Label4_14": 17,
    "Label4_15": 197,
    "Label4_2": 371,
    "Label4_3": 372,
    "Label4_32": 399,
    "Label4_33": 401,
    "Label4_34": 403,
    "Label4_35": 408,
    "Label4_36": 411,
    "Label4_37": 242,
    "Label4_38": 398,
    "Label4_39": 400,
    "Label4_4": 198,
    "Label4_40": 405,
    "Label4_41": 406,
    "Label4_42": 410,
    "Label4_43": 247,
    "Label4_44": 100,
    "Label4_45": 99,
    "Label4_46": 102,
    "Label4_47": 101,
    "Label4_48": 104,
    "Label4_49": 106,
    "Label4_50": 109,
    "Label4_51": 107,
    "Label4_52": 112,
    "Label4_53": 111,
    "Label4_54": 167,
    "Label4_55": 166,
    "Label4_56": 169,
    "Label4_57": 168,
    "Label4_58": 171,
    "Label4_59": 173,
    "Label4_6": 428,
    "Label4_60": 176,
    "Label4_61": 174,
    "Label4_62": 179,
    "Label4_63": 178,
    "Label4_7": 429,
    "Label4_8": 12,
    "Label4_9": 129,
    "Label5": 858,
    "Label5_23": 799,
    "Label5_24": 801,
    "Label5_26": 802,
    "Label5_27": 805,
    "Label5_28": 806,
    "Label5_29": 809,
    "Label5_30": 810,
    "Label5_31": 813,
    "Label5_32": 814,
    "Label5_33": 817,
    "Label5_34": 818,
    "Label5_35": 821,
    "Label5_36": 822,
    "Label5_52": 826,
    "Label5_54": 825,
    "Label5_56": 827,
    "Label6": 872,
    "Label6_1": 870,
    "Label6_2": 318,
    "Label7": 677,
    "Label7_1": 381,
    "Label7_2": 781,
    "Label7_3": 744,
    "Label7_4": 627,
    "Label7_5": 630,
    "Label7_6": 568,
    "Label7_7": 711,
    "Label8": 379,
    "Label8_1": 380,
    "Label8_10": 881,
    "Label8_18": 886,
    "Label8_19": 890,
    "Label8_2": 382,
    "Label8_3": 876,
    "Label8_4": 384,
    "Label9": 841,
    "Label9_1": 843,
    "Label9_2": 845,
    "Label9_3": 848,
    "Label9_4": 850,
    "My Details": 65,
    "name": 351,
    "Order Info": 0,
    "Orders": 538,
    "Orders_1": 597,
    "Planned_1": 388,
    "PowerBI1_2": 64,
    "PowerBI3": 61,
    "PowerBI3_2": 63,
    "Primary Cart": 0,
    "Primary Order Success": 0,
    "Primary Order Top Tab": 433,
    "Primary Order Top Tab_2": 434,
    "Primary Products": 0,
    "Product Gallery": 80,
    "Product Gallery_1": 147,
    "Profile": 0,
    "Rectangle1": 853,
    "Rectangle10": 869,
    "Rectangle11": 243,
    "Rectangle11_1": 248,
    "Rectangle2": 859,
    "Rectangle3": 862,
    "Rectangle3_2": 24,
    "Rectangle3_3": 789,
    "Rectangle4": 350,
    "Rectangle4_1": 414,
    "Rectangle4_2": 115,
    "Rectangle4_3": 184,
    "Rectangle4_4": 793,
    "Rectangle5": 647,
    "Rectangle5_1": 681,
    "Rectangle5_2": 748,
    "Rectangle5_3": 716,
    "Rectangle5_4": 587,
    "Rectangle5_5": 524,
    "Rectangle6": 880,
    "Rectangle7": 674,
    "Rectangle7_1": 373,
    "Rectangle7_2": 779,
    "Rectangle7_3": 742,
    "Rectangle7_4": 374,
    "Rectangle7_5": 624,
    "Rectangle7_6": 565,
    "Rectangle7_7": 709,
    "Rectangle9": 237,
    "Rectangle9_1": 366,
    "Retailer": 631,
    "Retailer_1": 570,
    "Search": 218,
    "Secondary Cart": 0,
    "Secondary Order Success": 0,
    "Secondary Orders": 0,
    "Secondary Products": 0,
    "Select Day Type": 0,
    "Side Bar": 1,
    "Side Bar_1": 337,
    "Side Bar_10": 311,
    "Side Bar_11": 325,
    "Side Bar_12": 648,
    "Side Bar_13": 584,
    "Side Bar_14": 715,
    "Side Bar_15": 749,
    "Side Bar_16": 523,
    "Side Bar_17": 682,
    "Side Bar_18": 586,
    "Side Bar_2": 66,
    "Side Bar_3": 69,
    "Side Bar_4": 521,
    "Side Bar_5": 837,
    "Side Bar_6": 136,
    "Side Bar_7": 255,
    "Side Bar_8": 275,
    "Side Bar_9": 296,
    "Start Screen": 0,
    "Start visit": 0,
    "StartDay": 0,
    "SubItems Gallery": 244,
    "Submit Day": 0,
    "Targets": 62,
    "TextInput1": 87,
    "TextInput2": 842,
    "TextInput2_1": 844,
    "TextInput2_10": 811,
    "TextInput2_11": 812,
    "TextInput2_12": 815,
    "TextInput2_13": 816,
    "TextInput2_14": 819,
    "TextInput2_15": 820,
    "TextInput2_16": 823,
    "TextInput2_17": 824,
    "TextInput2_2": 800,
    "TextInput2_3": 849,
    "TextInput2_4": 851,
    "TextInput2_6": 803,
    "TextInput2_7": 804,
    "TextInput2_8": 807,
    "TextInput2_9": 808,
    "TextInput5": 427,
    "TextInput5_1": 128,
    "TextInput5_2": 195,
    "TextInput7": 463,
    "TextInput7_3": 472,
    "TextInput7_4": 515,
    "TextInput7_5": 517,
    "TextInput7_6": 499,
    "TextInput7_7": 501,
    "TextInput7_8": 507,
    "TextInput7_9": 509,
    "Toggle1": 480,
    "Toggle1_1": 518,
    "total hours": 14,
    "Type": 15,
    "Unplanned_1": 387,
    "UploadedImage1": 477,
    "Visit Cart": 0,
    "Visit DatePicker": 345,
    "Visit History": 0,
    "Visit Products": 0,
    "Visit Search": 339,
    "Visits": 0,
    "VisitsInfoTopTab": 93,
    "VisitsInfoTopTab_1": 456,
    "VisitsInfoTopTab_2": 485,
    "VisitsInfoTopTab_3": 221,
    "VisitsInfoTopTab_4": 394,
    "VisitsInfoTopTab_5": 436
  },
  "ResourcesJsonIndices": {
    "Image-accept": 7,
    "Image-ad": 5,
    "Image-emp": 3,
    "Image-SampleImage": 0,
    "Image-WhatsApp Image 2022-05-13 at 1.06.35 PM": 6,
    "Image-zoxima logo": 4,
    "Image-zoxima logo only": 2,
    "Image-ZOXIMALOGO-removebg-preview": 1
  },
  "RuleScreenIdWithoutScreen": {},
  "TemplateVersions": {},
  "VolatileProperties": {
    "AnalysisLoadTime": 7.3885116,
    "ControlCount": {
      "298070d65dca4e3f9856e3d7dc529de0": 10,
      "30f86cc461bf48c695db5dfb932258e8": 1,
      "437f38a1c07644d28e03469a5b5ea640": 1,
      "45a728bf04444425ae2709bcd70ab8ba": 1,
      "48f9900d8e8f467da1e2aba0c74d22a6": 1,
      "51e914e59967428fb6455a4e2470627a": 1,
      "69894502ba10475d874bab19096f81b6": 19,
      "addMedia": 1,
      "b84e901362bb426a9025d47db36cd790": 28,
      "button": 51,
      "c24c8cdda8aa4592a2c19c5f7e216f34": 6,
      "c3cb5069657d462d988b819d87f57351": 1,
      "camera": 2,
      "checkbox": 1,
      "circle": 5,
      "combobox": 8,
      "dataCard": 4,
      "datepicker": 3,
      "fluidGrid": 4,
      "gallery": 38,
      "galleryTemplate": 38,
      "group": 67,
      "groupContainer": 12,
      "htmlViewer": 131,
      "icon": 59,
      "image": 25,
      "label": 309,
      "powerbi": 3,
      "rectangle": 32,
      "screen": 28,
      "text": 38,
      "toggleSwitch": 2
    },
    "DeserializationLoadTime": 9.9876447,
    "ErrorCount": 139
  },
  "WasLocalDatabaseReferencesEmpty": false
}